{
	"version": "0.3.14", 
	"suite": "unknown_suite", 
	"function_id": 3, 
	"function_name": "Rastrigin", 
	"maximization": false, 
	"algorithm": {"name": "BaseSCA", "info": "algorithm_info"},
	"attributes": ["evaluations", "raw_y"],
	"scenarios": [
		{"dimension": 2,
		"path": "data_f3_Rastrigin/IOHprofiler_f3_DIM2.dat",
		"runs": [
			{"instance": 5, "evals": 1001, "best": {"evals": 549, "y": 1.101993562337839, "x": [-2.7607460158230404, 1.4894996546539452]}},
			{"instance": 5, "evals": 1001, "best": {"evals": 217, "y": 0.03877848857362607, "x": [-3.7505536385034333, 1.4813792145647269]}},
			{"instance": 5, "evals": 1001, "best": {"evals": 418, "y": 3.448450321501368, "x": [-4.7138816027223385, 1.5183957568088473]}},
			{"instance": 5, "evals": 1001, "best": {"evals": 619, "y": 4.694603438929535, "x": [-4.698915610643663, 1.8875625345959386]}},
			{"instance": 5, "evals": 1001, "best": {"evals": 611, "y": 1.866619366941761, "x": [-3.714554661013824, 1.162010303219557]}}
		]}
	]
}
