{
	"version": "0.3.14", 
	"suite": "unknown_suite", 
	"function_id": 22, 
	"function_name": "Gallagher21", 
	"maximization": false, 
	"algorithm": {"name": "BaseSCA", "info": "algorithm_info"},
	"attributes": ["evaluations", "raw_y"],
	"scenarios": [
		{"dimension": 2,
		"path": "data_f22_Gallagher21/IOHprofiler_f22_DIM2.dat",
		"runs": [
			{"instance": 2, "evals": 1001, "best": {"evals": 609, "y": 2.3690023637167543e-05, "x": [-0.6067540054718281, -1.4508483273230073]}},
			{"instance": 2, "evals": 1001, "best": {"evals": 364, "y": 0.05169611813094772, "x": [-0.4994826413946396, -1.5730507221944894]}},
			{"instance": 2, "evals": 1001, "best": {"evals": 475, "y": 0.0017478696662594168, "x": [-1.1203753948736224, -1.1751691129791149]}},
			{"instance": 2, "evals": 1001, "best": {"evals": 302, "y": 3.485353682653168e-06, "x": [-0.5795230314386528, -1.472642723273539]}},
			{"instance": 2, "evals": 1001, "best": {"evals": 646, "y": 0.0011493675691867434, "x": [-1.2031662699163195, -1.167651384165651]}}
		]}
	]
}
